<mockup version="5.3" minAllowVersion="5.3" ID="4DC3C69D-625B-4B04-BBDA-8E3A60EFB993" platform="MtWeb" defaultW="1280" defaultH="1700" measureW="1280" measureH="1700" mobileScreenScale="0">
  <controls controlCount="119">
    <control controlID="3417EEF5-ECA8-E811-A42F-ACBC3297BA95" controlTypeID="Label" x="201" y="89" w="64" h="22" zOrder="0">
      <font family="%E5%BE%AE%E8%BD%AF%E9%9B%85%E9%BB%91" displayName="%E5%BE%AE%E8%BD%AF%E9%9B%85%E9%BB%91+Bold" postScript="" weightStyle="Bold" weight="700" isBold="True" isItalic="False"/>
      <text>%E8%AE%A2%E5%8D%95%E4%B8%AD%E5%BF%83</text>
      <textSize>16</textSize>
      <lineSpacing>0</lineSpacing>
      <textStyles>[fsBold]</textStyles>
      <useDefaultTextSize>False</useDefaultTextSize>
      <selectedIndex>-1</selectedIndex>
    </control>
    <control controlID="FE696790-5A90-46F1-B53A-A7459799E7EB" controlTypeID="Master" x="25" y="15" w="205" h="56" zOrder="1" masterID="C6373BAB-7887-467F-9A68-CD96F7E8F29D">
      <groupChildrenDescriptors>
        <control controlID="A88C5DAE-7677-42E4-92FF-10A4B93C2EC9" controlTypeID="Shape" x="0" y="0" w="60" h="56" zOrder="0">
          <font family="%E5%BE%AE%E8%BD%AF%E9%9B%85%E9%BB%91" displayName="%E5%BE%AE%E8%BD%AF%E9%9B%85%E9%BB%91" postScript="" weightStyle="Regular" weight="400" isBold="False" isItalic="False"/>
          <text>logo</text>
          <textSize>14</textSize>
          <selectedIndex>-1</selectedIndex>
        </control>
        <control controlID="6CB788F4-26C9-4D40-8982-53281C9E16B5" controlTypeID="Label" x="65" y="37" w="140" h="19" zOrder="1">
          <font family="%E5%BE%AE%E8%BD%AF%E9%9B%85%E9%BB%91" displayName="%E5%BE%AE%E8%BD%AF%E9%9B%85%E9%BB%91" postScript="" weightStyle="Regular" weight="400" isBold="False" isItalic="False"/>
          <text>%E6%99%93%E5%8F%AF%E5%B9%BF%E5%9C%BA%E5%95%86%E6%88%B7%E8%BF%90%E8%90%A5%E5%90%8E%E5%8F%B0</text>
          <lineSpacing>0</lineSpacing>
          <selectedIndex>-1</selectedIndex>
          <textSize>14</textSize>
        </control>
      </groupChildrenDescriptors>
      <textSize>14</textSize>
    </control>
    <control controlID="149B8DBE-DA2D-4DF5-9614-0B57AECDDD32" controlTypeID="Master" x="1053" y="15" w="207" h="47" zOrder="2" masterID="C383D48A-C7AB-4D44-8C5D-AAAFE9904004">
      <groupChildrenDescriptors>
        <control controlID="5CF710D2-CF9B-457B-82DE-B28A1C048C07" controlTypeID="Label" x="0" y="0" w="207" h="19" zOrder="0">
          <font family="%E5%BE%AE%E8%BD%AF%E9%9B%85%E9%BB%91" displayName="%E5%BE%AE%E8%BD%AF%E9%9B%85%E9%BB%91" postScript="" weightStyle="Regular" weight="400" isBold="False" isItalic="False"/>
          <text>%E6%AC%A2%E8%BF%8E%E6%82%A8%EF%BC%81%E5%88%98%E5%BE%B7%E5%8D%8E%EF%BC%8818586626598%EF%BC%89</text>
          <lineSpacing>0</lineSpacing>
          <selectedIndex>-1</selectedIndex>
          <textSize>14</textSize>
        </control>
        <control controlID="217647EC-137B-4982-8D11-1C05126121F2" controlTypeID="Button" x="137" y="23" w="70" h="24" zOrder="1">
          <links eventType="AtClick" animate="AmNone" animateAutoDelay="0" animateDuration="500">
            <link targetPageID="9EBDC779-D5CB-4277-93F3-0354D49ABF6E" linkType="ltPageLink" isApplyIncludePage="False" title="%E7%99%BB%E5%BD%95">
              <area shape="0" alt="" ID="{303AAC95-9E5C-40BE-B6D0-47D3A029285F}" coords="(0,0,70,24)"/>
            </link>
          </links>
          <font family="%E5%BE%AE%E8%BD%AF%E9%9B%85%E9%BB%91" displayName="%E5%BE%AE%E8%BD%AF%E9%9B%85%E9%BB%91" postScript="" weightStyle="Regular" weight="400" isBold="False" isItalic="False"/>
          <text>%E9%80%80%E5%87%BA</text>
          <lineSpacing>0</lineSpacing>
          <selectedIndex>-1</selectedIndex>
          <radius>4</radius>
          <textSize>14</textSize>
        </control>
      </groupChildrenDescriptors>
      <textSize>14</textSize>
    </control>
    <control controlID="9A03D59F-A5A1-4CD1-9E7C-2C36568F714B" controlTypeID="Master" x="25" y="89" w="150" h="415" zOrder="3" masterID="67A50A05-D791-44D7-B306-2AD2DE2A47D9">
      <groupChildrenDescriptors>
        <control controlID="FA1947EC-8CE9-45B2-858C-2D360AB68E80" controlTypeID="Accordion" x="0" y="0" w="150" h="415" zOrder="0">
          <links eventType="AtClick" animate="AmNone" animateAutoDelay="0" animateDuration="500">
            <link targetPageID="5BB939BE-FCFF-40ED-AD76-1EE5DEA28FCE" linkType="ltPageLink" isApplyIncludePage="False" title="%E9%A6%96%E9%A1%B5">
              <area shape="0" alt="" ID="{DB14AD93-F81D-4B96-AB3A-CD56209BC6C8}" coords="(1,1,149,30)"/>
            </link>
            <link targetPageID="3E7A7EBD-673D-40F7-8547-C18E261A637B" linkType="ltPageLink" isApplyIncludePage="False" title="%E5%95%86%E9%93%BA%E7%AE%A1%E7%90%86">
              <area shape="0" alt="" ID="{7F44BC96-789D-40D0-B662-23837575E9CA}" coords="(1,66,149,95)"/>
            </link>
            <link targetPageID="65509C04-59BE-43D7-957A-C04E26E7137B" linkType="ltPageLink" isApplyIncludePage="False" title="%E8%B4%A6%E5%8F%B7%E4%B8%AD%E5%BF%83">
              <area shape="0" alt="" ID="{67446BEC-5AD1-4327-BE58-075129259638}" coords="(1,95,149,124)"/>
            </link>
            <link targetPageID="D39C4A27-2F9B-4754-8BEF-DD7254D8E8EB" linkType="ltPageLink" isApplyIncludePage="False" title="%E8%AE%A2%E5%8D%95%E7%AE%A1%E7%90%86">
              <area shape="0" alt="" ID="{03EC30B7-1FC7-4209-BE04-97E0E0ABA180}" coords="(1,124,149,153)"/>
            </link>
            <link targetPageID="EFB1B18F-4822-4EEA-855E-970A25DF7324" linkType="ltPageLink" isApplyIncludePage="False" title="%E6%95%B0%E6%8D%AE%E4%B8%AD%E5%BF%83">
              <area shape="0" alt="" ID="{3ED47E5D-3CAF-4BA2-AEB0-425DFC04DF60}" coords="(1,153,149,182)"/>
            </link>
            <link targetPageID="DBB0D7F6-6525-4E15-8FA5-366465450724" linkType="ltPageLink" isApplyIncludePage="False" title="%E4%BF%83%E9%94%80%E7%AE%A1%E7%90%86">
              <area shape="0" alt="" ID="{B2C09447-F33B-4F2B-99D1-331E0D2870F4}" coords="(1,182,149,211)"/>
            </link>
            <link targetPageID="8FD92BBA-4178-49EF-93DB-EAEEB21C6884" linkType="ltPageLink" isApplyIncludePage="False" title="%E8%B4%A2%E5%8A%A1%E4%B8%AD%E5%BF%83">
              <area shape="0" alt="" ID="{2C48EBD8-2B82-4EE3-A364-34C8FE715B2D}" coords="(1,211,149,240)"/>
            </link>
            <link targetPageID="66BA56E7-2D92-4E23-9D16-A1AE31972D76" linkType="ltPageLink" isApplyIncludePage="False" title="%E9%93%B6%E8%A1%8C%E5%8D%A1%E7%AE%A1%E7%90%86">
              <area shape="0" alt="" ID="{E6738E25-E359-47F8-9B5A-1F40C2ADB740}" coords="(1,240,149,269)"/>
            </link>
            <link targetPageID="20FD2490-FEA8-E811-A42F-ACBC3297BA95" linkType="ltPageLink" isApplyIncludePage="False" title="%E8%AF%84%E4%BB%B7%E7%AE%A1%E7%90%86">
              <area shape="0" alt="" ID="{21CE4F68-6924-4AE3-9E09-B47D20A3B1F3}" coords="(1,269,149,298)"/>
            </link>
            <link targetPageID="663F95AC-E1B8-450C-B41F-55A77E039F75" linkType="ltPageLink" isApplyIncludePage="False" title="%E5%93%81%E7%B1%BB%E7%AE%A1%E7%90%86">
              <area shape="0" alt="" ID="{1FF3A1DF-3943-4C37-8198-C7024BB18F7F}" coords="(1,298,149,327)"/>
            </link>
            <link targetPageID="28A571AD-DAE8-4770-BB65-B3093C0A292E" linkType="ltPageLink" isApplyIncludePage="False" title="%E5%B8%AD%E4%BD%8D%E7%AE%A1%E7%90%86">
              <area shape="0" alt="" ID="{5A5BADA2-20FE-4544-B658-E808785E5D26}" coords="(1,327,149,356)"/>
            </link>
            <link targetPageID="414A76F0-C534-43F8-BA90-472C588500AD" linkType="ltPageLink" isApplyIncludePage="False" title="%E8%BF%90%E8%B4%B9%E8%AE%BE%E7%BD%AE">
              <area shape="0" alt="" ID="{293FA817-3884-4DB3-AE05-BD4409BFAF7F}" coords="(1,356,149,385)"/>
            </link>
            <link targetPageID="2501DBCE-2171-4E06-88B8-F59480A6BD49" linkType="ltPageLink" isApplyIncludePage="False" title="%E5%95%86%E5%93%81%E7%AE%A1%E7%90%86">
              <area shape="0" alt="" ID="{39CBCB30-5A7C-418A-8492-85019489ADFD}" coords="(1,385,149,414)"/>
            </link>
            <link targetPageID="A6F18FC5-6B18-4C91-B829-97447C88CEA6" linkType="ltPageLink" isApplyIncludePage="False" title="%E5%B8%B8%E8%A7%81%E9%97%AE%E9%A2%98">
              <area shape="0" alt="" ID="{373B6601-E014-4FFE-99C6-137043B54DBA}" coords="(1,385,150,414)"/>
            </link>
            <link targetPageID="" linkType="ltPageLink" isApplyIncludePage="False" title="%E6%94%AF%E4%BB%98%E5%AF%86%E7%A0%81">
              <area shape="0" alt="" ID="{5DC42CB5-AB2D-4732-B5CF-79A468C8E48D}" coords="(1,414,150,414)"/>
            </link>
            <link targetPageID="" linkType="ltPageLink" isApplyIncludePage="False" title="%E4%B8%AA%E4%BA%BA%E4%B8%AD%E5%BF%83">
              <area shape="0" alt="" ID="{F8511C5F-33F5-43D9-ACE8-8EB85BC6FAD3}" coords="(0,0,0,0)"/>
            </link>
          </links>
          <font family="%E5%BE%AE%E8%BD%AF%E9%9B%85%E9%BB%91" displayName="%E5%BE%AE%E8%BD%AF%E9%9B%85%E9%BB%91" postScript="" weightStyle="Regular" weight="400" isBold="False" isItalic="False"/>
          <text>%E9%A6%96%E9%A1%B5%0D%0A%E5%95%86%E9%93%BA%E7%AE%A1%E7%90%86%0D%0A%E8%B4%A6%E5%8F%B7%E4%B8%AD%E5%BF%83%0D%0A%E8%AE%A2%E5%8D%95%E7%AE%A1%E7%90%86%0D%0A%E6%95%B0%E6%8D%AE%E4%B8%AD%E5%BF%83%0D%0A%E4%BF%83%E9%94%80%E7%AE%A1%E7%90%86%0D%0A%E8%B4%A2%E5%8A%A1%E4%B8%AD%E5%BF%83%0D%0A%E9%93%B6%E8%A1%8C%E5%8D%A1%E7%AE%A1%E7%90%86%0D%0A%E8%AF%84%E4%BB%B7%E7%AE%A1%E7%90%86%0D%0A%E5%93%81%E7%B1%BB%E7%AE%A1%E7%90%86%0D%0A%E5%B8%AD%E4%BD%8D%E7%AE%A1%E7%90%86%0D%0A%E8%BF%90%E8%B4%B9%E8%AE%BE%E7%BD%AE%0D%0A%E5%95%86%E5%93%81%E7%AE%A1%E7%90%86%0D%0A%E5%B8%B8%E8%A7%81%E9%97%AE%E9%A2%98%0D%0A%E6%94%AF%E4%BB%98%E5%AF%86%E7%A0%81%0D%0A%E4%B8%AA%E4%BA%BA%E4%B8%AD%E5%BF%83%0D%0A</text>
          <textSize>14</textSize>
          <lineSpacing>0</lineSpacing>
        </control>
      </groupChildrenDescriptors>
      <textSize>14</textSize>
    </control>
    <control controlID="A9A4B9F0-40C9-4E73-81F7-876BBF7C1CAF" controlTypeID="Label" x="270" y="89" w="71" h="22" zOrder="4">
      <font family="%E5%BE%AE%E8%BD%AF%E9%9B%85%E9%BB%91" displayName="%E5%BE%AE%E8%BD%AF%E9%9B%85%E9%BB%91+Bold" postScript="" weightStyle="Bold" weight="700" isBold="True" isItalic="False"/>
      <text>%2F%E8%AE%A2%E5%8D%95%E8%AF%A6%E6%83%85</text>
      <textSize>16</textSize>
      <lineSpacing>0</lineSpacing>
      <textStyles>[fsBold]</textStyles>
      <useDefaultTextSize>False</useDefaultTextSize>
      <selectedIndex>-1</selectedIndex>
    </control>
    <control controlID="253C81C9-9114-4BB9-937B-8ECB91964901" controlTypeID="Button" x="510" y="682" w="70" h="28" zOrder="5">
      <font family="%E5%BE%AE%E8%BD%AF%E9%9B%85%E9%BB%91" displayName="%E5%BE%AE%E8%BD%AF%E9%9B%85%E9%BB%91" postScript="" weightStyle="Regular" weight="400" isBold="False" isItalic="False"/>
      <text>%E5%8F%96%E6%B6%88%E8%AE%A2%E5%8D%95</text>
      <lineSpacing>0</lineSpacing>
      <selectedIndex>-1</selectedIndex>
      <radius>4</radius>
      <textSize>14</textSize>
    </control>
    <control controlID="92DEDDA2-19B9-4E00-90B2-A17A5766C7D9" controlTypeID="Button" x="421" y="682" w="70" h="28" zOrder="6">
      <font family="%E5%BE%AE%E8%BD%AF%E9%9B%85%E9%BB%91" displayName="%E5%BE%AE%E8%BD%AF%E9%9B%85%E9%BB%91" postScript="" weightStyle="Regular" weight="400" isBold="False" isItalic="False"/>
      <text>%E5%88%B0%E5%BA%97%E7%A1%AE%E8%AE%A4</text>
      <lineSpacing>0</lineSpacing>
      <selectedIndex>-1</selectedIndex>
      <radius>4</radius>
      <textSize>14</textSize>
    </control>
    <control controlID="0117E505-B281-42AC-8F1E-CF387213BC28" controlTypeID="Label" x="211" y="148" w="137" h="19" zOrder="7">
      <font family="%E5%BE%AE%E8%BD%AF%E9%9B%85%E9%BB%91" displayName="%E5%BE%AE%E8%BD%AF%E9%9B%85%E9%BB%91" postScript="" weightStyle="Regular" weight="400" isBold="False" isItalic="False"/>
      <text>%E8%AE%A2%E5%8D%95%E5%8F%B7%EF%BC%9A1515151515</text>
      <lineSpacing>0</lineSpacing>
      <selectedIndex>-1</selectedIndex>
      <textSize>14</textSize>
    </control>
    <control controlID="4022FBE7-7BD7-46E3-97B2-B9EAEECCBD6B" controlTypeID="Label" x="211" y="177" w="219" h="19" zOrder="8">
      <font family="%E5%BE%AE%E8%BD%AF%E9%9B%85%E9%BB%91" displayName="%E5%BE%AE%E8%BD%AF%E9%9B%85%E9%BB%91" postScript="" weightStyle="Regular" weight="400" isBold="False" isItalic="False"/>
      <text>%E6%89%80%E5%B1%9E%E5%BA%97%E9%93%BA%EF%BC%9A151511524%EF%BC%88xxxx%E5%BA%97%E9%93%BA%EF%BC%89</text>
      <lineSpacing>0</lineSpacing>
      <selectedIndex>-1</selectedIndex>
      <textSize>14</textSize>
    </control>
    <control controlID="D4B318FE-0697-49FB-862A-EF256D4EDBF4" controlTypeID="Label" x="210" y="206" w="83" h="19" zOrder="9">
      <font family="%E5%BE%AE%E8%BD%AF%E9%9B%85%E9%BB%91" displayName="%E5%BE%AE%E8%BD%AF%E9%9B%85%E9%BB%91" postScript="" weightStyle="Regular" weight="400" isBold="False" isItalic="False"/>
      <text>%E7%8A%B6%E6%80%81%EF%BC%9A%E5%BE%85%E6%B6%88%E8%B4%B9</text>
      <lineSpacing>0</lineSpacing>
      <selectedIndex>-1</selectedIndex>
      <textSize>14</textSize>
    </control>
    <control controlID="24D3408F-05B9-42C2-B3B1-682CE3A51B91" controlTypeID="Label" x="211" y="264" w="82" h="19" zOrder="10">
      <font family="%E5%BE%AE%E8%BD%AF%E9%9B%85%E9%BB%91" displayName="%E5%BE%AE%E8%BD%AF%E9%9B%85%E9%BB%91" postScript="" weightStyle="Regular" weight="400" isBold="False" isItalic="False"/>
      <text>KTV%E7%89%B9%E4%BB%B7%E5%8C%85%E9%97%B4</text>
      <lineSpacing>0</lineSpacing>
      <useDefaultTextSize>False</useDefaultTextSize>
      <selectedIndex>-1</selectedIndex>
      <textSize>14</textSize>
    </control>
    <control controlID="F00BBF87-9664-40F3-9FB3-E7113735E384" controlTypeID="Label" x="211" y="235" w="187" h="19" zOrder="11">
      <font family="%E5%BE%AE%E8%BD%AF%E9%9B%85%E9%BB%91" displayName="%E5%BE%AE%E8%BD%AF%E9%9B%85%E9%BB%91" postScript="" weightStyle="Regular" weight="400" isBold="False" isItalic="False"/>
      <text>%E4%B8%8B%E5%8D%95%E6%97%B6%E9%97%B4%EF%BC%9A2018-08-08+12%3A12</text>
      <lineSpacing>0</lineSpacing>
      <selectedIndex>-1</selectedIndex>
      <textSize>14</textSize>
    </control>
    <control controlID="209E1F97-A099-4D36-9BAE-81697179F3A2" controlTypeID="Label" x="211" y="322" w="158" h="19" zOrder="12">
      <font family="%E5%BE%AE%E8%BD%AF%E9%9B%85%E9%BB%91" displayName="%E5%BE%AE%E8%BD%AF%E9%9B%85%E9%BB%91" postScript="" weightStyle="Regular" weight="400" isBold="False" isItalic="False"/>
      <text>%E9%A2%84%E7%BA%A6%E6%97%B6%E9%97%B4%EF%BC%9A8%E6%9C%8827%E6%97%A518%3A00</text>
      <lineSpacing>0</lineSpacing>
      <useDefaultTextSize>False</useDefaultTextSize>
      <selectedIndex>-1</selectedIndex>
      <textSize>14</textSize>
    </control>
    <control controlID="33792FE9-8E38-4A95-908F-620FC554EEF6" controlTypeID="Label" x="211" y="293" w="91" h="19" zOrder="13">
      <font family="%E5%BE%AE%E8%BD%AF%E9%9B%85%E9%BB%91" displayName="%E5%BE%AE%E8%BD%AF%E9%9B%85%E9%BB%91" postScript="" weightStyle="Regular" weight="400" isBold="False" isItalic="False"/>
      <text>%E4%B8%AD%E5%8C%85%2B200%E5%A5%97%E9%A4%90</text>
      <lineSpacing>0</lineSpacing>
      <useDefaultTextSize>False</useDefaultTextSize>
      <selectedIndex>-1</selectedIndex>
      <textSize>14</textSize>
    </control>
    <control controlID="AAE63F0D-C046-424E-88A3-BD90F38A6715" controlTypeID="Label" x="242" y="569" w="56" h="19" zOrder="14">
      <font family="%E5%BE%AE%E8%BD%AF%E9%9B%85%E9%BB%91" displayName="%E5%BE%AE%E8%BD%AF%E9%9B%85%E9%BB%91" postScript="" weightStyle="Regular" weight="400" isBold="False" isItalic="False"/>
      <text>%E5%8F%AF%E5%8F%A3%E5%8F%AF%E4%B9%90</text>
      <lineSpacing>0</lineSpacing>
      <useDefaultTextSize>False</useDefaultTextSize>
      <selectedIndex>-1</selectedIndex>
      <textSize>14</textSize>
    </control>
    <control controlID="D9D99A52-01B3-47F0-96F1-1C8838B1CCA4" controlTypeID="Label" x="433" y="650" w="153" h="19" zOrder="15">
      <font family="%E5%BE%AE%E8%BD%AF%E9%9B%85%E9%BB%91" displayName="%E5%BE%AE%E8%BD%AF%E9%9B%85%E9%BB%91" postScript="" weightStyle="Regular" weight="400" isBold="False" isItalic="False"/>
      <text>%E5%85%B113%E9%A1%B9++%E5%85%B1%E8%AE%A1%EF%BC%9A555.00%E5%85%83</text>
      <textAlign>HaRight</textAlign>
      <lineSpacing>0</lineSpacing>
      <useDefaultTextSize>False</useDefaultTextSize>
      <selectedIndex>-1</selectedIndex>
      <textSize>14</textSize>
    </control>
    <control controlID="3A6AF91F-B2B0-4585-A49B-DDB7145BF134" controlTypeID="Label" x="242" y="598" w="28" h="19" zOrder="16">
      <font family="%E5%BE%AE%E8%BD%AF%E9%9B%85%E9%BB%91" displayName="%E5%BE%AE%E8%BD%AF%E9%9B%85%E9%BB%91" postScript="" weightStyle="Regular" weight="400" isBold="False" isItalic="False"/>
      <text>%E7%BD%90%E8%A3%85</text>
      <lineSpacing>0</lineSpacing>
      <useDefaultTextSize>False</useDefaultTextSize>
      <selectedIndex>-1</selectedIndex>
      <textSize>14</textSize>
    </control>
    <control controlID="6F3CFBCD-6B37-4DFE-B3AA-F48D37706B77" controlTypeID="Label" x="513" y="569" w="14" h="19" zOrder="17">
      <font family="%E5%BE%AE%E8%BD%AF%E9%9B%85%E9%BB%91" displayName="%E5%BE%AE%E8%BD%AF%E9%9B%85%E9%BB%91" postScript="" weightStyle="Regular" weight="400" isBold="False" isItalic="False"/>
      <text>*2</text>
      <lineSpacing>0</lineSpacing>
      <useDefaultTextSize>False</useDefaultTextSize>
      <selectedIndex>-1</selectedIndex>
      <textSize>14</textSize>
    </control>
    <control controlID="CE615AFB-5E6C-4B54-ABBC-9D8D7EBA0FE0" controlTypeID="Shape" x="210" y="565" w="376" h="75" zOrder="18">
      <font family="%E5%BE%AE%E8%BD%AF%E9%9B%85%E9%BB%91" displayName="%E5%BE%AE%E8%BD%AF%E9%9B%85%E9%BB%91" postScript="" weightStyle="Regular" weight="400" isBold="False" isItalic="False"/>
      <textSize>14</textSize>
      <selectedIndex>-1</selectedIndex>
    </control>
    <control controlID="B7DB3BDA-9AF4-4600-B4DC-B3045F46C148" controlTypeID="Label" x="242" y="577" w="56" h="19" zOrder="19">
      <font family="%E5%BE%AE%E8%BD%AF%E9%9B%85%E9%BB%91" displayName="%E5%BE%AE%E8%BD%AF%E9%9B%85%E9%BB%91" postScript="" weightStyle="Regular" weight="400" isBold="False" isItalic="False"/>
      <text>%E5%95%86%E5%93%81%E5%90%8D%E7%A7%B0</text>
      <lineSpacing>0</lineSpacing>
      <selectedIndex>-1</selectedIndex>
      <textSize>14</textSize>
    </control>
    <control controlID="30ED5E81-4D6C-49AD-B2B3-7EBD94FEEE30" controlTypeID="Label" x="242" y="611" w="56" h="19" zOrder="20">
      <font family="%E5%BE%AE%E8%BD%AF%E9%9B%85%E9%BB%91" displayName="%E5%BE%AE%E8%BD%AF%E9%9B%85%E9%BB%91" postScript="" weightStyle="Regular" weight="400" isBold="False" isItalic="False"/>
      <text>%E5%95%86%E5%93%81%E8%A7%84%E6%A0%BC</text>
      <lineSpacing>0</lineSpacing>
      <selectedIndex>-1</selectedIndex>
      <textSize>14</textSize>
    </control>
    <control controlID="38BB9BBB-542E-4770-91EF-7E127BD6F1EB" controlTypeID="Label" x="537" y="577" w="39" h="19" zOrder="21">
      <font family="%E5%BE%AE%E8%BD%AF%E9%9B%85%E9%BB%91" displayName="%E5%BE%AE%E8%BD%AF%E9%9B%85%E9%BB%91" postScript="" weightStyle="Regular" weight="400" isBold="False" isItalic="False"/>
      <text>%C2%A515x2</text>
      <lineSpacing>0</lineSpacing>
      <selectedIndex>-1</selectedIndex>
      <textSize>14</textSize>
    </control>
    <control controlID="2E46DE0A-2EEB-41A2-B47D-D2D062D12D83" controlTypeID="Label" x="210" y="532" w="56" h="19" zOrder="22">
      <font family="%E5%BE%AE%E8%BD%AF%E9%9B%85%E9%BB%91" displayName="%E5%BE%AE%E8%BD%AF%E9%9B%85%E9%BB%91" postScript="" weightStyle="Regular" weight="400" isBold="False" isItalic="False"/>
      <text>%E5%8A%A0%E8%B4%AD%E8%8F%9C%E5%8D%95</text>
      <lineSpacing>0</lineSpacing>
      <selectedIndex>-1</selectedIndex>
      <textSize>14</textSize>
    </control>
    <control controlID="41CEF884-9222-4758-94C7-25AF8F6488E6" controlTypeID="Button" x="499" y="531" w="87" h="19" zOrder="23">
      <font family="%E5%BE%AE%E8%BD%AF%E9%9B%85%E9%BB%91" displayName="%E5%BE%AE%E8%BD%AF%E9%9B%85%E9%BB%91" postScript="" weightStyle="Regular" weight="400" isBold="False" isItalic="False"/>
      <text>%E4%BF%AE%E6%94%B9</text>
      <lineSpacing>0</lineSpacing>
      <selectedIndex>-1</selectedIndex>
      <textSize>14</textSize>
    </control>
    <control controlID="98C29EBC-9416-4D2B-AC27-8830D2A61C64" controlTypeID="Label" x="210" y="351" w="159" h="19" zOrder="24">
      <font family="%E5%BE%AE%E8%BD%AF%E9%9B%85%E9%BB%91" displayName="%E5%BE%AE%E8%BD%AF%E9%9B%85%E9%BB%91" postScript="" weightStyle="Regular" weight="400" isBold="False" isItalic="False"/>
      <text>%E9%A2%84%E7%BA%A6%E6%89%8B%E6%9C%BA%EF%BC%9A18585858585</text>
      <lineSpacing>0</lineSpacing>
      <useDefaultTextSize>False</useDefaultTextSize>
      <selectedIndex>-1</selectedIndex>
      <textSize>14</textSize>
    </control>
    <control controlID="C389AFC8-8F8F-4768-88B4-91776C303F4D" controlTypeID="Label" x="210" y="497" w="294" h="19" zOrder="25">
      <font family="%E5%BE%AE%E8%BD%AF%E9%9B%85%E9%BB%91" displayName="%E5%BE%AE%E8%BD%AF%E9%9B%85%E9%BB%91" postScript="" weightStyle="Regular" weight="400" isBold="False" isItalic="False"/>
      <text>%E5%A4%87%E6%B3%A8%EF%BC%9A%E9%98%BF%E8%90%A8%E5%BE%B7%E5%8F%91%E7%9A%84%E5%8F%91%E7%94%9F%E7%9A%84%E5%8F%91%E7%94%9F%E5%A4%A7%E5%B8%88%E6%B3%95%E5%B8%88%E6%89%93%E5%8F%91%E6%89%93%E5%8F%91</text>
      <lineSpacing>0</lineSpacing>
      <useDefaultTextSize>False</useDefaultTextSize>
      <selectedIndex>-1</selectedIndex>
      <textSize>14</textSize>
    </control>
    <control controlID="85BB37E6-25EA-4EB3-9967-26D434CD1D0C" controlTypeID="Label" x="210" y="406" w="50" h="19" zOrder="26">
      <font family="%E5%BE%AE%E8%BD%AF%E9%9B%85%E9%BB%91" displayName="%E5%BE%AE%E8%BD%AF%E9%9B%85%E9%BB%91" postScript="" weightStyle="Regular" weight="400" isBold="False" isItalic="False"/>
      <text>%E6%95%B0%E9%87%8F%EF%BC%9A4</text>
      <lineSpacing>0</lineSpacing>
      <selectedIndex>-1</selectedIndex>
      <textSize>14</textSize>
    </control>
    <control controlID="AB620F80-41C2-4D6E-9EA4-F014A13E8286" controlTypeID="Label" x="210" y="380" w="80" h="19" zOrder="27">
      <font family="%E5%BE%AE%E8%BD%AF%E9%9B%85%E9%BB%91" displayName="%E5%BE%AE%E8%BD%AF%E9%9B%85%E9%BB%91" postScript="" weightStyle="Regular" weight="400" isBold="False" isItalic="False"/>
      <text>%E5%8D%95%E4%BB%B7%EF%BC%9A100%E5%85%83</text>
      <lineSpacing>0</lineSpacing>
      <selectedIndex>-1</selectedIndex>
      <textSize>14</textSize>
    </control>
    <control controlID="69F04BA9-AB58-4B89-8196-8B49C61BF0BA" controlTypeID="Label" x="210" y="436" w="108" h="19" zOrder="28">
      <font family="%E5%BE%AE%E8%BD%AF%E9%9B%85%E9%BB%91" displayName="%E5%BE%AE%E8%BD%AF%E9%9B%85%E9%BB%91" postScript="" weightStyle="Regular" weight="400" isBold="False" isItalic="False"/>
      <text>%E5%85%B1%E8%AE%A1%EF%BC%9A1000.00%E5%85%83</text>
      <lineSpacing>0</lineSpacing>
      <selectedIndex>-1</selectedIndex>
      <textSize>14</textSize>
    </control>
    <control controlID="DAC8BEB4-4019-48BC-AA8F-4C51C2136BB2" controlTypeID="Label" x="306" y="380" w="80" h="19" zOrder="29">
      <font family="%E5%BE%AE%E8%BD%AF%E9%9B%85%E9%BB%91" displayName="%E5%BE%AE%E8%BD%AF%E9%9B%85%E9%BB%91" postScript="" weightStyle="Regular" weight="400" isBold="False" isItalic="False"/>
      <text>%E5%8E%9F%E4%BB%B7%EF%BC%9A150%E5%85%83</text>
      <lineSpacing>0</lineSpacing>
      <selectedIndex>-1</selectedIndex>
      <textSize>14</textSize>
    </control>
    <control controlID="0B66986E-0613-4A49-8282-A39901EAB275" controlTypeID="TextArea" x="210" y="465" w="420" h="23" zOrder="30">
      <font family="%E5%BE%AE%E8%BD%AF%E9%9B%85%E9%BB%91" displayName="%E5%BE%AE%E8%BD%AF%E9%9B%85%E9%BB%91" postScript="" weightStyle="Regular" weight="400" isBold="False" isItalic="False"/>
      <text>%E4%BC%98%E6%83%A0%E8%AF%B4%E6%98%8E%EF%BC%9A%EF%BC%88%E4%BC%9A%E5%91%98%E5%8D%A1%E6%89%93%E6%8A%98%2F%E6%89%93%E6%8A%98%E5%88%B8%2F%E6%8A%B5%E6%89%A3%E5%88%B8%2F%E6%BB%A1%E5%87%8F%E5%88%B8%E4%BC%98%E6%83%A026.00%E5%85%83%EF%BC%89</text>
      <selectedIndex>-1</selectedIndex>
      <textSize>14</textSize>
    </control>
    <control controlID="6ECAEB5D-40C1-4A9C-AFC6-72873482F775" controlTypeID="Label" x="334" y="436" w="112" h="19" zOrder="31">
      <font family="%E5%BE%AE%E8%BD%AF%E9%9B%85%E9%BB%91" displayName="%E5%BE%AE%E8%BD%AF%E9%9B%85%E9%BB%91" postScript="" weightStyle="Regular" weight="400" isBold="False" isItalic="False"/>
      <text>%E6%94%AF%E4%BB%98%E6%96%B9%E5%BC%8F%EF%BC%9A%E6%94%AF%E4%BB%98%E5%AE%9D</text>
      <lineSpacing>0</lineSpacing>
      <selectedIndex>-1</selectedIndex>
      <textSize>14</textSize>
    </control>
    <control controlID="5F2C0364-343F-45BF-8C18-03F504A60EF4" controlTypeID="PopupPanel" x="1117" y="674" w="46" h="46" zOrder="32">
      <caption>%E4%BF%AE%E6%94%B9%E8%AE%A2%E5%8D%95</caption>
      <groupChildrenDescriptors>
        <control controlID="149F4315-0417-4B55-AD4A-63B57DCB4D23" controlTypeID="Panel" x="0" y="0" w="1280" h="720" zOrder="0">
          <locked>True</locked>
          <color>1879048192</color>
          <borderVisible>False</borderVisible>
          <canMove>False</canMove>
          <alias>background</alias>
          <groupChildrenDescriptors>
            <control controlID="EED3C579-2F1B-49E7-B2CC-48CBBE46BA27" controlTypeID="Border" x="0" y="0" w="1280" h="720" zOrder="0">
              <borderVisible>False</borderVisible>
              <alias>borderLayer</alias>
              <textSize>14</textSize>
            </control>
          </groupChildrenDescriptors>
          <thinkness>1</thinkness>
          <textSize>14</textSize>
        </control>
        <control controlID="04116FA1-65E7-4063-8275-C830C83582D5" controlTypeID="PopupPanelContent" x="24" y="24" w="1230" h="696" zOrder="1">
          <color>16777215</color>
          <alias>content</alias>
          <groupChildrenDescriptors>
            <control controlID="C3D7C50D-0A21-41C5-B06A-329C6B29F435" controlTypeID="Shape" x="658" y="114" w="572" h="582" zOrder="0">
              <font family="%E5%BE%AE%E8%BD%AF%E9%9B%85%E9%BB%91" displayName="%E5%BE%AE%E8%BD%AF%E9%9B%85%E9%BB%91" postScript="" weightStyle="Regular" weight="400" isBold="False" isItalic="False"/>
              <textSize>14</textSize>
              <selectedIndex>-1</selectedIndex>
            </control>
            <control controlID="30025E27-6CDA-4ACE-8619-B3D01A29AC45" controlTypeID="Shape" x="668" y="184" w="211" h="64" zOrder="1">
              <font family="%E5%BE%AE%E8%BD%AF%E9%9B%85%E9%BB%91" displayName="%E5%BE%AE%E8%BD%AF%E9%9B%85%E9%BB%91" postScript="" weightStyle="Regular" weight="400" isBold="False" isItalic="False"/>
              <textSize>14</textSize>
              <selectedIndex>-1</selectedIndex>
            </control>
            <control controlID="8E5106F9-C674-4329-B9C7-B7B6BF9D1BAF" controlTypeID="Label" x="668" y="124" w="56" h="19" zOrder="2">
              <font family="%E5%BE%AE%E8%BD%AF%E9%9B%85%E9%BB%91" displayName="%E5%BE%AE%E8%BD%AF%E9%9B%85%E9%BB%91" postScript="" weightStyle="Regular" weight="400" isBold="False" isItalic="False"/>
              <text>%E4%BF%AE%E6%94%B9%E8%AE%A2%E5%8D%95</text>
              <lineSpacing>0</lineSpacing>
              <selectedIndex>-1</selectedIndex>
              <textSize>14</textSize>
            </control>
            <control controlID="18D65E44-8279-4643-9A44-05F6D1D22287" controlTypeID="CompositeComboBox" x="668" y="153" w="211" h="24" zOrder="3">
              <groupChildrenDescriptors>
                <control controlID="A991B078-BD03-42D6-89CB-3E83662F5BBB" controlTypeID="TextInput" x="0" y="0" w="188" h="24" zOrder="0">
                  <locked>True</locked>
                  <canMove>False</canMove>
                  <alias>input</alias>
                  <font family="%E5%BE%AE%E8%BD%AF%E9%9B%85%E9%BB%91" displayName="%E5%BE%AE%E8%BD%AF%E9%9B%85%E9%BB%91" postScript="" weightStyle="Regular" weight="400" isBold="False" isItalic="False"/>
                  <text>%E6%88%BF%E9%97%B41</text>
                  <lineSpacing>0</lineSpacing>
                  <selectedIndex>-1</selectedIndex>
                  <textSize>14</textSize>
                </control>
                <control controlID="B5473E52-BEF2-434E-8A4D-2B2796F1B9A5" controlTypeID="Button" x="187" y="0" w="24" h="24" zOrder="1">
                  <locked>True</locked>
                  <canMove>False</canMove>
                  <alias>button</alias>
                  <font family="%E5%BE%AE%E8%BD%AF%E9%9B%85%E9%BB%91" displayName="%E5%BE%AE%E8%BD%AF%E9%9B%85%E9%BB%91" postScript="" weightStyle="Regular" weight="400" isBold="False" isItalic="False"/>
                  <lineSpacing>0</lineSpacing>
                  <selectedIndex>-1</selectedIndex>
                  <radius>0</radius>
                  <textSize>14</textSize>
                </control>
                <control controlID="4C04CCEA-5D7C-41ED-ACA1-9F641BC22D11" controlTypeID="List" x="0" y="24" w="211" h="98" zOrder="2">
                  <isShow>False</isShow>
                  <canMove>False</canMove>
                  <alias>dropDown</alias>
                  <font family="%E5%BE%AE%E8%BD%AF%E9%9B%85%E9%BB%91" displayName="%E5%BE%AE%E8%BD%AF%E9%9B%85%E9%BB%91" postScript="" weightStyle="Regular" weight="400" isBold="False" isItalic="False"/>
                  <text>%E6%88%BF%E9%97%B41%0D%0A%E6%88%BF%E9%97%B42%0D%0A%E6%88%BF%E9%97%B43%0D%0A%E6%88%BF%E9%97%B44</text>
                  <textSize>14</textSize>
                  <lineSpacing>0</lineSpacing>
                  <itemHeight>24</itemHeight>
                  <interlaceColor>4294967295</interlaceColor>
                </control>
              </groupChildrenDescriptors>
              <baseHeight>24</baseHeight>
              <font family="%E5%BE%AE%E8%BD%AF%E9%9B%85%E9%BB%91"/>
              <textSize>14</textSize>
            </control>
            <control controlID="9225FFA3-9F62-4C5B-B478-60BD2316AA01" controlTypeID="Shape" x="734" y="190" w="64" h="22" zOrder="4">
              <font family="%E5%BE%AE%E8%BD%AF%E9%9B%85%E9%BB%91" displayName="%E5%BE%AE%E8%BD%AF%E9%9B%85%E9%BB%91" postScript="" weightStyle="Regular" weight="400" isBold="False" isItalic="False"/>
              <text>%E8%A7%84%E6%A0%BC1</text>
              <textSize>14</textSize>
              <selectedIndex>-1</selectedIndex>
            </control>
            <control controlID="A446DEF0-DEC8-482C-A934-3D9955FAB4F4" controlTypeID="Shape" x="810" y="190" w="64" h="22" zOrder="5">
              <font family="%E5%BE%AE%E8%BD%AF%E9%9B%85%E9%BB%91" displayName="%E5%BE%AE%E8%BD%AF%E9%9B%85%E9%BB%91" postScript="" weightStyle="Regular" weight="400" isBold="False" isItalic="False"/>
              <text>%E8%A7%84%E6%A0%BC2</text>
              <textSize>14</textSize>
              <selectedIndex>-1</selectedIndex>
            </control>
            <control controlID="4D4C6E23-26C9-4775-AF88-5AD6B0D15EDD" controlTypeID="Label" x="675" y="189" w="28" h="19" zOrder="6">
              <font family="%E5%BE%AE%E8%BD%AF%E9%9B%85%E9%BB%91" displayName="%E5%BE%AE%E8%BD%AF%E9%9B%85%E9%BB%91" postScript="" weightStyle="Regular" weight="400" isBold="False" isItalic="False"/>
              <text>%E8%A7%84%E6%A0%BC</text>
              <lineSpacing>0</lineSpacing>
              <selectedIndex>-1</selectedIndex>
              <textSize>14</textSize>
            </control>
            <control controlID="FC1EC6A3-59F2-416E-9B5B-1F31A9B7EA93" controlTypeID="Label" x="675" y="218" w="28" h="19" zOrder="7">
              <font family="%E5%BE%AE%E8%BD%AF%E9%9B%85%E9%BB%91" displayName="%E5%BE%AE%E8%BD%AF%E9%9B%85%E9%BB%91" postScript="" weightStyle="Regular" weight="400" isBold="False" isItalic="False"/>
              <text>%E6%95%B0%E9%87%8F</text>
              <lineSpacing>0</lineSpacing>
              <selectedIndex>-1</selectedIndex>
              <textSize>14</textSize>
            </control>
            <control controlID="F79CC26E-E0FF-4243-BF58-F82A6714D57F" controlTypeID="Label" x="795" y="220" w="8" h="19" zOrder="8">
              <font family="%E5%BE%AE%E8%BD%AF%E9%9B%85%E9%BB%91" displayName="%E5%BE%AE%E8%BD%AF%E9%9B%85%E9%BB%91" postScript="" weightStyle="Regular" weight="400" isBold="False" isItalic="False"/>
              <text>4</text>
              <lineSpacing>0</lineSpacing>
              <selectedIndex>-1</selectedIndex>
              <textSize>14</textSize>
            </control>
            <control controlID="A9538E99-BBF6-4C67-BAF0-E3BA7C1AF797" controlTypeID="Icon" x="810" y="218" w="24" h="24" zOrder="9">
              <icon>
                <ID/>
                <iconFontName>jdIonicons</iconFontName>
                <iconCode>62151</iconCode>
              </icon>
              <URL>D08755C22A9B40B6BF65036DEC8B44B4.svg</URL>
              <textSize>14</textSize>
            </control>
            <control controlID="F7AF3660-F8DD-477E-95AF-5C633CD89EF6" controlTypeID="Icon" x="761" y="218" w="24" h="24" zOrder="10">
              <icon>
                <ID/>
                <iconFontName>jdIonicons</iconFontName>
                <iconCode>62196</iconCode>
              </icon>
              <URL>3E8A114DA0C702D4B04AC41CD80EAA9D.svg</URL>
              <textSize>14</textSize>
            </control>
            <control controlID="96598F04-2080-44CD-B0A1-C4EF01D5AB58" controlTypeID="RadioButton" x="0" y="0" w="120" h="19" zOrder="11">
              <font family="%E5%BE%AE%E8%BD%AF%E9%9B%85%E9%BB%91" displayName="%E5%BE%AE%E8%BD%AF%E9%9B%85%E9%BB%91" postScript="" weightStyle="Regular" weight="400" isBold="False" isItalic="False"/>
              <text>%E5%8D%95%E9%80%89%E6%8C%89%E9%92%AE</text>
              <lineSpacing>0</lineSpacing>
              <selectedIndex>-1</selectedIndex>
              <size>13</size>
              <textSize>14</textSize>
            </control>
            <control controlID="777CE45A-E7AC-4D9D-B6CE-75E4BF4918D9" controlTypeID="Shape" x="668" y="295" w="81" h="70" zOrder="12">
              <font family="%E5%BE%AE%E8%BD%AF%E9%9B%85%E9%BB%91" displayName="%E5%BE%AE%E8%BD%AF%E9%9B%85%E9%BB%91" postScript="" weightStyle="Regular" weight="400" isBold="False" isItalic="False"/>
              <text>%E5%88%86%E7%B1%BB</text>
              <textSize>14</textSize>
              <selectedIndex>-1</selectedIndex>
            </control>
            <control controlID="66754034-6550-4589-94E5-FB12D227FAA4" controlTypeID="Shape" x="668" y="365" w="81" h="70" zOrder="13">
              <font family="%E5%BE%AE%E8%BD%AF%E9%9B%85%E9%BB%91" displayName="%E5%BE%AE%E8%BD%AF%E9%9B%85%E9%BB%91" postScript="" weightStyle="Regular" weight="400" isBold="False" isItalic="False"/>
              <text>%E5%88%86%E7%B1%BB</text>
              <textSize>14</textSize>
              <selectedIndex>-1</selectedIndex>
            </control>
            <control controlID="E6018908-BD00-495B-9078-56BE788167CC" controlTypeID="Shape" x="668" y="436" w="81" h="70" zOrder="14">
              <font family="%E5%BE%AE%E8%BD%AF%E9%9B%85%E9%BB%91" displayName="%E5%BE%AE%E8%BD%AF%E9%9B%85%E9%BB%91" postScript="" weightStyle="Regular" weight="400" isBold="False" isItalic="False"/>
              <text>%E5%88%86%E7%B1%BB</text>
              <textSize>14</textSize>
              <selectedIndex>-1</selectedIndex>
            </control>
            <control controlID="EFE701E5-BC6D-4CE3-9CC6-39E7FB75C6DF" controlTypeID="Shape" x="668" y="278" w="269" h="55" zOrder="15">
              <font family="%E5%BE%AE%E8%BD%AF%E9%9B%85%E9%BB%91" displayName="%E5%BE%AE%E8%BD%AF%E9%9B%85%E9%BB%91" postScript="" weightStyle="Regular" weight="400" isBold="False" isItalic="False"/>
              <textSize>14</textSize>
              <selectedIndex>-1</selectedIndex>
            </control>
            <control controlID="F4EBB533-A0A7-4D0C-A09B-28A4307FBEDC" controlTypeID="Label" x="678" y="283" w="56" h="19" zOrder="16">
              <font family="%E5%BE%AE%E8%BD%AF%E9%9B%85%E9%BB%91" displayName="%E5%BE%AE%E8%BD%AF%E9%9B%85%E9%BB%91" postScript="" weightStyle="Regular" weight="400" isBold="False" isItalic="False"/>
              <text>%E5%95%86%E5%93%81%E5%90%8D%E7%A7%B0</text>
              <lineSpacing>0</lineSpacing>
              <selectedIndex>-1</selectedIndex>
              <textSize>14</textSize>
            </control>
            <control controlID="EA5A96C7-2D64-40F9-9E65-859B5D5DA7CB" controlTypeID="Label" x="678" y="309" w="33" h="19" zOrder="17">
              <font family="%E5%BE%AE%E8%BD%AF%E9%9B%85%E9%BB%91" displayName="%E5%BE%AE%E8%BD%AF%E9%9B%85%E9%BB%91" postScript="" weightStyle="Regular" weight="400" isBold="False" isItalic="False"/>
              <text>%E8%A7%84%E6%A0%BC1</text>
              <lineSpacing>0</lineSpacing>
              <selectedIndex>-1</selectedIndex>
              <textSize>14</textSize>
            </control>
            <control controlID="4AFEC848-CEA8-4C0E-BC07-3215A74B93FF" controlTypeID="Label" x="721" y="309" w="35" h="19" zOrder="18">
              <font family="%E5%BE%AE%E8%BD%AF%E9%9B%85%E9%BB%91" displayName="%E5%BE%AE%E8%BD%AF%E9%9B%85%E9%BB%91" postScript="" weightStyle="Regular" weight="400" isBold="False" isItalic="False"/>
              <text>%E8%A7%84%E6%A0%BC2</text>
              <lineSpacing>0</lineSpacing>
              <selectedIndex>-1</selectedIndex>
              <textSize>14</textSize>
            </control>
            <control controlID="D51B9034-F776-4431-A99D-222FDA433B27" controlTypeID="Label" x="807" y="291" w="34" h="27" zOrder="19">
              <font family="%E5%BE%AE%E8%BD%AF%E9%9B%85%E9%BB%91" displayName="%E5%BE%AE%E8%BD%AF%E9%9B%85%E9%BB%91" postScript="" weightStyle="Regular" weight="400" isBold="False" isItalic="False"/>
              <text>%C2%A510</text>
              <textSize>20</textSize>
              <lineSpacing>0</lineSpacing>
              <useDefaultTextSize>False</useDefaultTextSize>
              <selectedIndex>-1</selectedIndex>
            </control>
            <control controlID="28EE88A4-C735-4CFB-A7D2-666B667B8891" controlTypeID="Label" x="880" y="291" w="10" h="27" zOrder="20">
              <font family="%E5%BE%AE%E8%BD%AF%E9%9B%85%E9%BB%91" displayName="%E5%BE%AE%E8%BD%AF%E9%9B%85%E9%BB%91" postScript="" weightStyle="Regular" weight="400" isBold="False" isItalic="False"/>
              <text>5</text>
              <textSize>20</textSize>
              <lineSpacing>0</lineSpacing>
              <useDefaultTextSize>False</useDefaultTextSize>
              <selectedIndex>-1</selectedIndex>
            </control>
            <control controlID="FAFFDD2E-57E5-4C46-A0C1-1853B7A4D62D" controlTypeID="Shape" x="668" y="333" w="269" h="55" zOrder="21">
              <font family="%E5%BE%AE%E8%BD%AF%E9%9B%85%E9%BB%91" displayName="%E5%BE%AE%E8%BD%AF%E9%9B%85%E9%BB%91" postScript="" weightStyle="Regular" weight="400" isBold="False" isItalic="False"/>
              <textSize>14</textSize>
              <selectedIndex>-1</selectedIndex>
            </control>
            <control controlID="D7D8DBC0-C3B3-441C-8C71-A3C68E07BEEB" controlTypeID="Label" x="678" y="338" w="56" h="19" zOrder="22">
              <font family="%E5%BE%AE%E8%BD%AF%E9%9B%85%E9%BB%91" displayName="%E5%BE%AE%E8%BD%AF%E9%9B%85%E9%BB%91" postScript="" weightStyle="Regular" weight="400" isBold="False" isItalic="False"/>
              <text>%E5%95%86%E5%93%81%E5%90%8D%E7%A7%B0</text>
              <lineSpacing>0</lineSpacing>
              <selectedIndex>-1</selectedIndex>
              <textSize>14</textSize>
            </control>
            <control controlID="1271008F-527E-4CB5-BA9F-EBAB161120E2" controlTypeID="Label" x="678" y="364" w="33" h="19" zOrder="23">
              <font family="%E5%BE%AE%E8%BD%AF%E9%9B%85%E9%BB%91" displayName="%E5%BE%AE%E8%BD%AF%E9%9B%85%E9%BB%91" postScript="" weightStyle="Regular" weight="400" isBold="False" isItalic="False"/>
              <text>%E8%A7%84%E6%A0%BC1</text>
              <lineSpacing>0</lineSpacing>
              <selectedIndex>-1</selectedIndex>
              <textSize>14</textSize>
            </control>
            <control controlID="5B97EC5E-2768-4A9C-8D4B-37821B13432F" controlTypeID="Label" x="721" y="364" w="35" h="19" zOrder="24">
              <font family="%E5%BE%AE%E8%BD%AF%E9%9B%85%E9%BB%91" displayName="%E5%BE%AE%E8%BD%AF%E9%9B%85%E9%BB%91" postScript="" weightStyle="Regular" weight="400" isBold="False" isItalic="False"/>
              <text>%E8%A7%84%E6%A0%BC2</text>
              <lineSpacing>0</lineSpacing>
              <selectedIndex>-1</selectedIndex>
              <textSize>14</textSize>
            </control>
            <control controlID="15DB2C81-DA9F-4D16-9960-72E185D94B3C" controlTypeID="Label" x="807" y="346" w="34" h="27" zOrder="25">
              <font family="%E5%BE%AE%E8%BD%AF%E9%9B%85%E9%BB%91" displayName="%E5%BE%AE%E8%BD%AF%E9%9B%85%E9%BB%91" postScript="" weightStyle="Regular" weight="400" isBold="False" isItalic="False"/>
              <text>%C2%A510</text>
              <textSize>20</textSize>
              <lineSpacing>0</lineSpacing>
              <useDefaultTextSize>False</useDefaultTextSize>
              <selectedIndex>-1</selectedIndex>
            </control>
            <control controlID="536D210B-9418-4873-9226-7B621B0DE7D6" controlTypeID="Label" x="880" y="346" w="10" h="27" zOrder="26">
              <font family="%E5%BE%AE%E8%BD%AF%E9%9B%85%E9%BB%91" displayName="%E5%BE%AE%E8%BD%AF%E9%9B%85%E9%BB%91" postScript="" weightStyle="Regular" weight="400" isBold="False" isItalic="False"/>
              <text>5</text>
              <textSize>20</textSize>
              <lineSpacing>0</lineSpacing>
              <useDefaultTextSize>False</useDefaultTextSize>
              <selectedIndex>-1</selectedIndex>
            </control>
            <control controlID="8CF38E45-C197-4DB2-A913-21C588BC5254" controlTypeID="Shape" x="668" y="388" w="269" h="55" zOrder="27">
              <font family="%E5%BE%AE%E8%BD%AF%E9%9B%85%E9%BB%91" displayName="%E5%BE%AE%E8%BD%AF%E9%9B%85%E9%BB%91" postScript="" weightStyle="Regular" weight="400" isBold="False" isItalic="False"/>
              <textSize>14</textSize>
              <selectedIndex>-1</selectedIndex>
            </control>
            <control controlID="6E655BC8-F94A-482E-8958-EE0CF7360E8F" controlTypeID="Label" x="678" y="393" w="56" h="19" zOrder="28">
              <font family="%E5%BE%AE%E8%BD%AF%E9%9B%85%E9%BB%91" displayName="%E5%BE%AE%E8%BD%AF%E9%9B%85%E9%BB%91" postScript="" weightStyle="Regular" weight="400" isBold="False" isItalic="False"/>
              <text>%E5%95%86%E5%93%81%E5%90%8D%E7%A7%B0</text>
              <lineSpacing>0</lineSpacing>
              <selectedIndex>-1</selectedIndex>
              <textSize>14</textSize>
            </control>
            <control controlID="B589A2CC-DFDD-47A0-B673-AF33650353E8" controlTypeID="Label" x="678" y="419" w="33" h="19" zOrder="29">
              <font family="%E5%BE%AE%E8%BD%AF%E9%9B%85%E9%BB%91" displayName="%E5%BE%AE%E8%BD%AF%E9%9B%85%E9%BB%91" postScript="" weightStyle="Regular" weight="400" isBold="False" isItalic="False"/>
              <text>%E8%A7%84%E6%A0%BC1</text>
              <lineSpacing>0</lineSpacing>
              <selectedIndex>-1</selectedIndex>
              <textSize>14</textSize>
            </control>
            <control controlID="8488AD8B-A6AD-4B59-9A1D-E73290AD6E58" controlTypeID="Label" x="721" y="419" w="35" h="19" zOrder="30">
              <font family="%E5%BE%AE%E8%BD%AF%E9%9B%85%E9%BB%91" displayName="%E5%BE%AE%E8%BD%AF%E9%9B%85%E9%BB%91" postScript="" weightStyle="Regular" weight="400" isBold="False" isItalic="False"/>
              <text>%E8%A7%84%E6%A0%BC2</text>
              <lineSpacing>0</lineSpacing>
              <selectedIndex>-1</selectedIndex>
              <textSize>14</textSize>
            </control>
            <control controlID="B04111FA-AAA9-4718-BD29-711F13D8BBF7" controlTypeID="Label" x="807" y="401" w="34" h="27" zOrder="31">
              <font family="%E5%BE%AE%E8%BD%AF%E9%9B%85%E9%BB%91" displayName="%E5%BE%AE%E8%BD%AF%E9%9B%85%E9%BB%91" postScript="" weightStyle="Regular" weight="400" isBold="False" isItalic="False"/>
              <text>%C2%A510</text>
              <textSize>20</textSize>
              <lineSpacing>0</lineSpacing>
              <useDefaultTextSize>False</useDefaultTextSize>
              <selectedIndex>-1</selectedIndex>
            </control>
            <control controlID="E15DB1A0-7D5A-4D0B-8E1D-4ED709731733" controlTypeID="Label" x="880" y="401" w="10" h="27" zOrder="32">
              <font family="%E5%BE%AE%E8%BD%AF%E9%9B%85%E9%BB%91" displayName="%E5%BE%AE%E8%BD%AF%E9%9B%85%E9%BB%91" postScript="" weightStyle="Regular" weight="400" isBold="False" isItalic="False"/>
              <text>5</text>
              <textSize>20</textSize>
              <lineSpacing>0</lineSpacing>
              <useDefaultTextSize>False</useDefaultTextSize>
              <selectedIndex>-1</selectedIndex>
            </control>
            <control controlID="9FBCEAD6-6CE3-4452-9EFC-E0C5C5415E3D" controlTypeID="Shape" x="668" y="443" w="269" h="55" zOrder="33">
              <font family="%E5%BE%AE%E8%BD%AF%E9%9B%85%E9%BB%91" displayName="%E5%BE%AE%E8%BD%AF%E9%9B%85%E9%BB%91" postScript="" weightStyle="Regular" weight="400" isBold="False" isItalic="False"/>
              <textSize>14</textSize>
              <selectedIndex>-1</selectedIndex>
            </control>
            <control controlID="FAB29AD5-A883-4174-8DBC-036490C40D7F" controlTypeID="Label" x="678" y="448" w="56" h="19" zOrder="34">
              <font family="%E5%BE%AE%E8%BD%AF%E9%9B%85%E9%BB%91" displayName="%E5%BE%AE%E8%BD%AF%E9%9B%85%E9%BB%91" postScript="" weightStyle="Regular" weight="400" isBold="False" isItalic="False"/>
              <text>%E5%95%86%E5%93%81%E5%90%8D%E7%A7%B0</text>
              <lineSpacing>0</lineSpacing>
              <selectedIndex>-1</selectedIndex>
              <textSize>14</textSize>
            </control>
            <control controlID="9565F72A-234B-4452-81D4-79F163CA88DC" controlTypeID="Label" x="678" y="474" w="33" h="19" zOrder="35">
              <font family="%E5%BE%AE%E8%BD%AF%E9%9B%85%E9%BB%91" displayName="%E5%BE%AE%E8%BD%AF%E9%9B%85%E9%BB%91" postScript="" weightStyle="Regular" weight="400" isBold="False" isItalic="False"/>
              <text>%E8%A7%84%E6%A0%BC1</text>
              <lineSpacing>0</lineSpacing>
              <selectedIndex>-1</selectedIndex>
              <textSize>14</textSize>
            </control>
            <control controlID="41B43136-85BD-4631-96F0-DAFCF39627DC" controlTypeID="Label" x="721" y="474" w="35" h="19" zOrder="36">
              <font family="%E5%BE%AE%E8%BD%AF%E9%9B%85%E9%BB%91" displayName="%E5%BE%AE%E8%BD%AF%E9%9B%85%E9%BB%91" postScript="" weightStyle="Regular" weight="400" isBold="False" isItalic="False"/>
              <text>%E8%A7%84%E6%A0%BC2</text>
              <lineSpacing>0</lineSpacing>
              <selectedIndex>-1</selectedIndex>
              <textSize>14</textSize>
            </control>
            <control controlID="261FC8E5-4078-4DBB-BD49-F120C83DACBD" controlTypeID="Label" x="807" y="456" w="34" h="27" zOrder="37">
              <font family="%E5%BE%AE%E8%BD%AF%E9%9B%85%E9%BB%91" displayName="%E5%BE%AE%E8%BD%AF%E9%9B%85%E9%BB%91" postScript="" weightStyle="Regular" weight="400" isBold="False" isItalic="False"/>
              <text>%C2%A510</text>
              <textSize>20</textSize>
              <lineSpacing>0</lineSpacing>
              <useDefaultTextSize>False</useDefaultTextSize>
              <selectedIndex>-1</selectedIndex>
            </control>
            <control controlID="3900D57F-A689-482C-8A39-EB78C20CDAC2" controlTypeID="Label" x="880" y="456" w="10" h="27" zOrder="38">
              <font family="%E5%BE%AE%E8%BD%AF%E9%9B%85%E9%BB%91" displayName="%E5%BE%AE%E8%BD%AF%E9%9B%85%E9%BB%91" postScript="" weightStyle="Regular" weight="400" isBold="False" isItalic="False"/>
              <text>5</text>
              <textSize>20</textSize>
              <lineSpacing>0</lineSpacing>
              <useDefaultTextSize>False</useDefaultTextSize>
              <selectedIndex>-1</selectedIndex>
            </control>
            <control controlID="591CDA68-ED17-4959-9FE6-7CEE7C7CEB9F" controlTypeID="Shape" x="668" y="498" w="269" h="55" zOrder="39">
              <font family="%E5%BE%AE%E8%BD%AF%E9%9B%85%E9%BB%91" displayName="%E5%BE%AE%E8%BD%AF%E9%9B%85%E9%BB%91" postScript="" weightStyle="Regular" weight="400" isBold="False" isItalic="False"/>
              <textSize>14</textSize>
              <selectedIndex>-1</selectedIndex>
            </control>
            <control controlID="1BD26F73-EB9E-4A64-A3CA-6EA99752BB09" controlTypeID="Label" x="678" y="503" w="56" h="19" zOrder="40">
              <font family="%E5%BE%AE%E8%BD%AF%E9%9B%85%E9%BB%91" displayName="%E5%BE%AE%E8%BD%AF%E9%9B%85%E9%BB%91" postScript="" weightStyle="Regular" weight="400" isBold="False" isItalic="False"/>
              <text>%E5%95%86%E5%93%81%E5%90%8D%E7%A7%B0</text>
              <lineSpacing>0</lineSpacing>
              <selectedIndex>-1</selectedIndex>
              <textSize>14</textSize>
            </control>
            <control controlID="86A9C50D-68DF-4E62-9232-AAA36119189A" controlTypeID="Label" x="678" y="529" w="33" h="19" zOrder="41">
              <font family="%E5%BE%AE%E8%BD%AF%E9%9B%85%E9%BB%91" displayName="%E5%BE%AE%E8%BD%AF%E9%9B%85%E9%BB%91" postScript="" weightStyle="Regular" weight="400" isBold="False" isItalic="False"/>
              <text>%E8%A7%84%E6%A0%BC1</text>
              <lineSpacing>0</lineSpacing>
              <selectedIndex>-1</selectedIndex>
              <textSize>14</textSize>
            </control>
            <control controlID="3E11691B-A3E2-43FB-A879-9EC2D15671E4" controlTypeID="Label" x="721" y="529" w="35" h="19" zOrder="42">
              <font family="%E5%BE%AE%E8%BD%AF%E9%9B%85%E9%BB%91" displayName="%E5%BE%AE%E8%BD%AF%E9%9B%85%E9%BB%91" postScript="" weightStyle="Regular" weight="400" isBold="False" isItalic="False"/>
              <text>%E8%A7%84%E6%A0%BC2</text>
              <lineSpacing>0</lineSpacing>
              <selectedIndex>-1</selectedIndex>
              <textSize>14</textSize>
            </control>
            <control controlID="D32A293F-B1EA-4110-83FC-C68A47522C61" controlTypeID="Label" x="807" y="511" w="34" h="27" zOrder="43">
              <font family="%E5%BE%AE%E8%BD%AF%E9%9B%85%E9%BB%91" displayName="%E5%BE%AE%E8%BD%AF%E9%9B%85%E9%BB%91" postScript="" weightStyle="Regular" weight="400" isBold="False" isItalic="False"/>
              <text>%C2%A510</text>
              <textSize>20</textSize>
              <lineSpacing>0</lineSpacing>
              <useDefaultTextSize>False</useDefaultTextSize>
              <selectedIndex>-1</selectedIndex>
            </control>
            <control controlID="7564FE3D-AC09-4DB2-9EFC-6CC7BAD55F50" controlTypeID="Label" x="880" y="511" w="10" h="27" zOrder="44">
              <font family="%E5%BE%AE%E8%BD%AF%E9%9B%85%E9%BB%91" displayName="%E5%BE%AE%E8%BD%AF%E9%9B%85%E9%BB%91" postScript="" weightStyle="Regular" weight="400" isBold="False" isItalic="False"/>
              <text>5</text>
              <textSize>20</textSize>
              <lineSpacing>0</lineSpacing>
              <useDefaultTextSize>False</useDefaultTextSize>
              <selectedIndex>-1</selectedIndex>
            </control>
            <control controlID="847F2A51-7CB3-42A8-A2BC-DF7BFCFFD24B" controlTypeID="Icon" x="897" y="292" w="24" h="24" zOrder="45">
              <icon>
                <ID/>
                <iconFontName>jdIonicons</iconFontName>
                <iconCode>62297</iconCode>
              </icon>
              <URL>A74ACDBBC3EE487C9CDF84F8F9700C7C.svg</URL>
              <textSize>14</textSize>
            </control>
            <control controlID="756ABF75-CE61-4C48-8EF6-3131FBB6D590" controlTypeID="Icon" x="849" y="292" w="24" h="24" zOrder="46">
              <icon>
                <ID/>
                <iconFontName>jdIonicons</iconFontName>
                <iconCode>62377</iconCode>
              </icon>
              <URL>C12822B8AE3890BE32A0274B6AF9E5B5.svg</URL>
              <textSize>14</textSize>
            </control>
            <control controlID="2D330342-66F7-4E03-9BC0-24ACA7741856" controlTypeID="Icon" x="897" y="348" w="24" h="24" zOrder="47">
              <icon>
                <ID/>
                <iconFontName>jdIonicons</iconFontName>
                <iconCode>62297</iconCode>
              </icon>
              <URL>A74ACDBBC3EE487C9CDF84F8F9700C7C.svg</URL>
              <textSize>14</textSize>
            </control>
            <control controlID="206F7032-F364-46C5-92B8-CF93A9A4E779" controlTypeID="Icon" x="849" y="348" w="24" h="24" zOrder="48">
              <icon>
                <ID/>
                <iconFontName>jdIonicons</iconFontName>
                <iconCode>62377</iconCode>
              </icon>
              <URL>C12822B8AE3890BE32A0274B6AF9E5B5.svg</URL>
              <textSize>14</textSize>
            </control>
            <control controlID="752D7633-3861-4AEC-99FF-BDF958B5A5A8" controlTypeID="Icon" x="897" y="404" w="24" h="24" zOrder="49">
              <icon>
                <ID/>
                <iconFontName>jdIonicons</iconFontName>
                <iconCode>62297</iconCode>
              </icon>
              <URL>A74ACDBBC3EE487C9CDF84F8F9700C7C.svg</URL>
              <textSize>14</textSize>
            </control>
            <control controlID="5EFE68B6-5CF7-4E75-9414-CB83C6522C97" controlTypeID="Icon" x="849" y="404" w="24" h="24" zOrder="50">
              <icon>
                <ID/>
                <iconFontName>jdIonicons</iconFontName>
                <iconCode>62377</iconCode>
              </icon>
              <URL>C12822B8AE3890BE32A0274B6AF9E5B5.svg</URL>
              <textSize>14</textSize>
            </control>
            <control controlID="E9A9EB13-BB1D-4D59-B852-3176391FDB66" controlTypeID="Icon" x="897" y="456" w="24" h="24" zOrder="51">
              <icon>
                <ID/>
                <iconFontName>jdIonicons</iconFontName>
                <iconCode>62297</iconCode>
              </icon>
              <URL>A74ACDBBC3EE487C9CDF84F8F9700C7C.svg</URL>
              <textSize>14</textSize>
            </control>
            <control controlID="5E9A282D-EA90-4F8C-87C1-4750D3E4526F" controlTypeID="Icon" x="849" y="456" w="24" h="24" zOrder="52">
              <icon>
                <ID/>
                <iconFontName>jdIonicons</iconFontName>
                <iconCode>62377</iconCode>
              </icon>
              <URL>C12822B8AE3890BE32A0274B6AF9E5B5.svg</URL>
              <textSize>14</textSize>
            </control>
            <control controlID="B70F6518-E5FC-4A9D-B544-51D8E3060EA7" controlTypeID="Icon" x="897" y="512" w="24" h="24" zOrder="53">
              <icon>
                <ID/>
                <iconFontName>jdIonicons</iconFontName>
                <iconCode>62297</iconCode>
              </icon>
              <URL>A74ACDBBC3EE487C9CDF84F8F9700C7C.svg</URL>
              <textSize>14</textSize>
            </control>
            <control controlID="0A139F43-5AA3-4C1F-B610-93D9382A2060" controlTypeID="Icon" x="849" y="512" w="24" h="24" zOrder="54">
              <icon>
                <ID/>
                <iconFontName>jdIonicons</iconFontName>
                <iconCode>62377</iconCode>
              </icon>
              <URL>C12822B8AE3890BE32A0274B6AF9E5B5.svg</URL>
              <textSize>14</textSize>
            </control>
            <control controlID="770C3F75-3C4E-4170-923B-279F2384DDD8" controlTypeID="Label" x="895" y="206" w="27" h="19" zOrder="55">
              <font family="%E5%BE%AE%E8%BD%AF%E9%9B%85%E9%BB%91" displayName="%E5%BE%AE%E8%BD%AF%E9%9B%85%E9%BB%91" postScript="" weightStyle="Regular" weight="400" isBold="False" isItalic="False"/>
              <text>%E6%B7%BB%E5%8A%A0</text>
              <lineSpacing>0</lineSpacing>
              <selectedIndex>-1</selectedIndex>
              <textSize>14</textSize>
            </control>
            <control controlID="128D7AF4-8E75-4A4C-BE46-9FCD82191E29" controlTypeID="Label" x="835" y="589" w="100" h="19" zOrder="56">
              <font family="%E5%BE%AE%E8%BD%AF%E9%9B%85%E9%BB%91" displayName="%E5%BE%AE%E8%BD%AF%E9%9B%85%E9%BB%91" postScript="" weightStyle="Regular" weight="400" isBold="False" isItalic="False"/>
              <text>%E5%85%B1%E8%AE%A1%EF%BC%9A555.00%E5%85%83</text>
              <lineSpacing>0</lineSpacing>
              <useDefaultTextSize>False</useDefaultTextSize>
              <selectedIndex>-1</selectedIndex>
              <textSize>14</textSize>
            </control>
            <control controlID="9D4D8A34-792A-4521-A5F7-239A97787E34" controlTypeID="Label" x="886" y="558" w="50" h="19" zOrder="57">
              <font family="%E5%BE%AE%E8%BD%AF%E9%9B%85%E9%BB%91" displayName="%E5%BE%AE%E8%BD%AF%E9%9B%85%E9%BB%91" postScript="" weightStyle="Regular" weight="400" isBold="False" isItalic="False"/>
              <text>%E6%95%B0%E9%87%8F%EF%BC%9A6</text>
              <lineSpacing>0</lineSpacing>
              <useDefaultTextSize>False</useDefaultTextSize>
              <selectedIndex>-1</selectedIndex>
              <textSize>14</textSize>
            </control>
            <control controlID="9DA008F7-13F1-4529-B478-9E0F8D78147C" controlTypeID="Button" x="784" y="648" w="70" h="28" zOrder="58">
              <font family="%E5%BE%AE%E8%BD%AF%E9%9B%85%E9%BB%91" displayName="%E5%BE%AE%E8%BD%AF%E9%9B%85%E9%BB%91" postScript="" weightStyle="Regular" weight="400" isBold="False" isItalic="False"/>
              <text>%E7%A1%AE%E5%AE%9A</text>
              <lineSpacing>0</lineSpacing>
              <selectedIndex>-1</selectedIndex>
              <radius>4</radius>
              <textSize>14</textSize>
            </control>
            <control controlID="E7752123-856E-432F-BE22-5865747E0C4E" controlTypeID="Button" x="866" y="647" w="70" h="28" zOrder="59">
              <font family="%E5%BE%AE%E8%BD%AF%E9%9B%85%E9%BB%91" displayName="%E5%BE%AE%E8%BD%AF%E9%9B%85%E9%BB%91" postScript="" weightStyle="Regular" weight="400" isBold="False" isItalic="False"/>
              <text>%E5%8F%96%E6%B6%88</text>
              <lineSpacing>0</lineSpacing>
              <selectedIndex>-1</selectedIndex>
              <radius>4</radius>
              <textSize>14</textSize>
            </control>
          </groupChildrenDescriptors>
          <textSize>14</textSize>
        </control>
      </groupChildrenDescriptors>
      <textSize>14</textSize>
    </control>
    <control controlID="831C25EC-C819-41A9-83E0-7FAFEE09AE66" controlTypeID="PopupPanel" x="841" y="629" w="46" h="46" zOrder="33">
      <groupChildrenDescriptors>
        <control controlID="7B872384-F9EF-46C6-AB2D-AA406C6BE89A" controlTypeID="Panel" x="0" y="0" w="1280" h="720" zOrder="0">
          <locked>True</locked>
          <color>1879048192</color>
          <borderVisible>False</borderVisible>
          <canMove>False</canMove>
          <alias>background</alias>
          <groupChildrenDescriptors>
            <control controlID="3F79DD4A-8FA8-4333-B96A-BA256B852310" controlTypeID="Border" x="0" y="0" w="1280" h="720" zOrder="0">
              <borderVisible>False</borderVisible>
              <alias>borderLayer</alias>
              <textSize>14</textSize>
            </control>
          </groupChildrenDescriptors>
          <thinkness>1</thinkness>
          <textSize>14</textSize>
        </control>
        <control controlID="6EDDFDF6-796B-4AC8-BECF-1ED5CC1265E9" controlTypeID="PopupPanelContent" x="460" y="216" w="453" h="260" zOrder="1">
          <color>16777215</color>
          <alias>content</alias>
          <groupChildrenDescriptors>
            <control controlID="7D61B262-89FD-4B01-8981-49DE26222E6D" controlTypeID="Shape" x="0" y="0" w="453" h="260" zOrder="0">
              <font family="%E5%BE%AE%E8%BD%AF%E9%9B%85%E9%BB%91" displayName="%E5%BE%AE%E8%BD%AF%E9%9B%85%E9%BB%91" postScript="" weightStyle="Regular" weight="400" isBold="False" isItalic="False"/>
              <textSize>14</textSize>
              <selectedIndex>-1</selectedIndex>
            </control>
            <control controlID="A27FA66D-0415-4F28-B0D6-A03A13901157" controlTypeID="Label" x="10" y="10" w="112" h="19" zOrder="1">
              <font family="%E5%BE%AE%E8%BD%AF%E9%9B%85%E9%BB%91" displayName="%E5%BE%AE%E8%BD%AF%E9%9B%85%E9%BB%91" postScript="" weightStyle="Regular" weight="400" isBold="False" isItalic="False"/>
              <text>%E8%AE%A2%E5%8D%95%E5%88%B0%E5%BA%97%E6%B6%88%E8%B4%B9%E7%A1%AE%E8%AE%A4</text>
              <lineSpacing>0</lineSpacing>
              <selectedIndex>-1</selectedIndex>
              <textSize>14</textSize>
            </control>
            <control controlID="06236E3B-3FFE-4C89-9B0F-00E2135E90CF" controlTypeID="Label" x="50" y="69" w="41" h="19" zOrder="2">
              <font family="%E5%BE%AE%E8%BD%AF%E9%9B%85%E9%BB%91" displayName="%E5%BE%AE%E8%BD%AF%E9%9B%85%E9%BB%91" postScript="" weightStyle="Regular" weight="400" isBold="False" isItalic="False"/>
              <text>%E6%B6%88%E8%B4%B9%E7%A0%81</text>
              <lineSpacing>0</lineSpacing>
              <selectedIndex>-1</selectedIndex>
              <textSize>14</textSize>
            </control>
            <control controlID="8E8E7D14-5EFF-4A30-B38C-360A686699D9" controlTypeID="TextInput" x="101" y="66" w="300" h="24" zOrder="3">
              <font family="%E5%BE%AE%E8%BD%AF%E9%9B%85%E9%BB%91" displayName="%E5%BE%AE%E8%BD%AF%E9%9B%85%E9%BB%91" postScript="" weightStyle="Regular" weight="400" isBold="False" isItalic="False"/>
              <lineSpacing>0</lineSpacing>
              <selectedIndex>-1</selectedIndex>
              <textSize>14</textSize>
            </control>
            <control controlID="41D9AE0C-25AE-460E-9511-7BF4DC04DDFF" controlTypeID="Button" x="142" y="180" w="70" h="28" zOrder="4">
              <font family="%E5%BE%AE%E8%BD%AF%E9%9B%85%E9%BB%91" displayName="%E5%BE%AE%E8%BD%AF%E9%9B%85%E9%BB%91" postScript="" weightStyle="Regular" weight="400" isBold="False" isItalic="False"/>
              <text>%E7%A1%AE%E5%AE%9A</text>
              <lineSpacing>0</lineSpacing>
              <selectedIndex>-1</selectedIndex>
              <radius>4</radius>
              <textSize>14</textSize>
            </control>
            <control controlID="389EAB88-D0AF-455C-B452-07A881094B66" controlTypeID="Button" x="240" y="180" w="70" h="28" zOrder="5">
              <font family="%E5%BE%AE%E8%BD%AF%E9%9B%85%E9%BB%91" displayName="%E5%BE%AE%E8%BD%AF%E9%9B%85%E9%BB%91" postScript="" weightStyle="Regular" weight="400" isBold="False" isItalic="False"/>
              <text>%E5%8F%96%E6%B6%88</text>
              <lineSpacing>0</lineSpacing>
              <selectedIndex>-1</selectedIndex>
              <radius>4</radius>
              <textSize>14</textSize>
            </control>
            <control controlID="F9CF5638-6624-437B-B696-1F88EA9E5C6D" controlTypeID="CompositeComboBox" x="101" y="111" w="300" h="24" zOrder="6">
              <groupChildrenDescriptors>
                <control controlID="06AB5C0E-6B2D-4AC6-9989-7CF48D780D20" controlTypeID="TextInput" x="0" y="0" w="277" h="24" zOrder="0">
                  <locked>True</locked>
                  <canMove>False</canMove>
                  <alias>input</alias>
                  <font family="%E5%BE%AE%E8%BD%AF%E9%9B%85%E9%BB%91" displayName="%E5%BE%AE%E8%BD%AF%E9%9B%85%E9%BB%91" postScript="" weightStyle="Regular" weight="400" isBold="False" isItalic="False"/>
                  <text>%E6%9D%A1%E7%9B%AE%E4%B8%80</text>
                  <lineSpacing>0</lineSpacing>
                  <selectedIndex>-1</selectedIndex>
                  <textSize>14</textSize>
                </control>
                <control controlID="8379F306-A6E7-4B08-987C-C0550929F4D8" controlTypeID="Button" x="276" y="0" w="24" h="24" zOrder="1">
                  <locked>True</locked>
                  <canMove>False</canMove>
                  <alias>button</alias>
                  <font family="%E5%BE%AE%E8%BD%AF%E9%9B%85%E9%BB%91" displayName="%E5%BE%AE%E8%BD%AF%E9%9B%85%E9%BB%91" postScript="" weightStyle="Regular" weight="400" isBold="False" isItalic="False"/>
                  <lineSpacing>0</lineSpacing>
                  <selectedIndex>-1</selectedIndex>
                  <radius>0</radius>
                  <textSize>14</textSize>
                </control>
                <control controlID="9DC2FBBB-7DF6-481F-AE73-C76F76CF5070" controlTypeID="List" x="0" y="24" w="300" h="98" zOrder="2">
                  <isShow>False</isShow>
                  <canMove>False</canMove>
                  <alias>dropDown</alias>
                  <font family="%E5%BE%AE%E8%BD%AF%E9%9B%85%E9%BB%91" displayName="%E5%BE%AE%E8%BD%AF%E9%9B%85%E9%BB%91" postScript="" weightStyle="Regular" weight="400" isBold="False" isItalic="False"/>
                  <text>%E6%9D%A1%E7%9B%AE%E4%B8%80%0D%0A%E6%9D%A1%E7%9B%AE%E4%BA%8C%0D%0A%E6%9D%A1%E7%9B%AE%E4%B8%89%0D%0A%E6%9D%A1%E7%9B%AE%E5%9B%9B</text>
                  <textSize>14</textSize>
                  <lineSpacing>0</lineSpacing>
                  <itemHeight>24</itemHeight>
                  <interlaceColor>4294967295</interlaceColor>
                </control>
              </groupChildrenDescriptors>
              <baseHeight>24</baseHeight>
              <font family="%E5%BE%AE%E8%BD%AF%E9%9B%85%E9%BB%91"/>
              <textSize>14</textSize>
            </control>
            <control controlID="20CAB2B1-B4BD-4CBB-BA7C-B09DD1388C70" controlTypeID="Label" x="50" y="113" w="28" h="19" zOrder="7">
              <font family="%E5%BE%AE%E8%BD%AF%E9%9B%85%E9%BB%91" displayName="%E5%BE%AE%E8%BD%AF%E9%9B%85%E9%BB%91" postScript="" weightStyle="Regular" weight="400" isBold="False" isItalic="False"/>
              <text>%E5%B8%AD%E4%BD%8D</text>
              <lineSpacing>0</lineSpacing>
              <selectedIndex>-1</selectedIndex>
              <textSize>14</textSize>
            </control>
          </groupChildrenDescriptors>
          <textSize>14</textSize>
        </control>
      </groupChildrenDescriptors>
      <textSize>14</textSize>
    </control>
  </controls>
  <param>
    <backgroundColor>4294967295</backgroundColor>
    <fontSize>14</fontSize>
    <fontFamily>%E5%BE%AE%E8%BD%AF%E9%9B%85%E9%BB%91</fontFamily>
    <guideLines/>
  </param>
</mockup>