<mockup version="5.3" minAllowVersion="5.3" ID="9EBDC779-D5CB-4277-93F3-0354D49ABF6E" platform="MtWeb" defaultW="1280" defaultH="720" measureW="1280" measureH="720" mobileScreenScale="0">
  <controls controlCount="8">
    <control controlID="BD052A31-9543-4940-9ADF-E4D1E57C03F4" controlTypeID="Label" x="507" y="349" w="28" h="19" zOrder="0">
      <font family="%E5%BE%AE%E8%BD%AF%E9%9B%85%E9%BB%91" displayName="%E5%BE%AE%E8%BD%AF%E9%9B%85%E9%BB%91" postScript="" weightStyle="Regular" weight="400" isBold="False" isItalic="False"/>
      <text>%E8%B4%A6%E5%8F%B7</text>
      <lineSpacing>0</lineSpacing>
      <selectedIndex>-1</selectedIndex>
    </control>
    <control controlID="7D6D9257-A5E6-4E0A-8DB1-0EAE13F71BC0" controlTypeID="Image" x="573" y="113" w="150" h="150" zOrder="1"/>
    <control controlID="28DC7EAB-B153-4C40-961A-F1E183EBAB0B" controlTypeID="TextInput" x="541" y="346" w="232" h="24" zOrder="2">
      <font family="%E5%BE%AE%E8%BD%AF%E9%9B%85%E9%BB%91" displayName="%E5%BE%AE%E8%BD%AF%E9%9B%85%E9%BB%91" postScript="" weightStyle="Regular" weight="400" isBold="False" isItalic="False"/>
      <lineSpacing>0</lineSpacing>
      <selectedIndex>-1</selectedIndex>
    </control>
    <control controlID="EB62D1AF-7E84-4E62-ADB4-3CB9CFFF1BAC" controlTypeID="Label" x="507" y="395" w="27" h="19" zOrder="3">
      <font family="%E5%BE%AE%E8%BD%AF%E9%9B%85%E9%BB%91" displayName="%E5%BE%AE%E8%BD%AF%E9%9B%85%E9%BB%91" postScript="" weightStyle="Regular" weight="400" isBold="False" isItalic="False"/>
      <text>%E5%AF%86%E7%A0%81</text>
      <lineSpacing>0</lineSpacing>
      <selectedIndex>-1</selectedIndex>
    </control>
    <control controlID="77500EB7-9D6B-4A4D-80EF-DFE8F6985EEE" controlTypeID="TextInput" x="541" y="392" w="232" h="24" zOrder="4">
      <font family="%E5%BE%AE%E8%BD%AF%E9%9B%85%E9%BB%91" displayName="%E5%BE%AE%E8%BD%AF%E9%9B%85%E9%BB%91" postScript="" weightStyle="Regular" weight="400" isBold="False" isItalic="False"/>
      <lineSpacing>0</lineSpacing>
      <selectedIndex>-1</selectedIndex>
    </control>
    <control controlID="CFADCBD3-DF95-45EE-8802-CFD08CFF589F" controlTypeID="Button" x="557" y="476" w="182" h="28" zOrder="5">
      <font family="%E5%BE%AE%E8%BD%AF%E9%9B%85%E9%BB%91" displayName="%E5%BE%AE%E8%BD%AF%E9%9B%85%E9%BB%91" postScript="" weightStyle="Regular" weight="400" isBold="False" isItalic="False"/>
      <text>%E7%99%BB%E5%BD%95</text>
      <lineSpacing>0</lineSpacing>
      <selectedIndex>-1</selectedIndex>
      <radius>4</radius>
    </control>
    <control controlID="8558201A-9F26-494D-B0EF-A9F09711985B" controlTypeID="Button" x="557" y="514" w="182" h="28" zOrder="6">
      <font family="%E5%BE%AE%E8%BD%AF%E9%9B%85%E9%BB%91" displayName="%E5%BE%AE%E8%BD%AF%E9%9B%85%E9%BB%91" postScript="" weightStyle="Regular" weight="400" isBold="False" isItalic="False"/>
      <text>%E6%89%BE%E5%9B%9E%E5%AF%86%E7%A0%81</text>
      <lineSpacing>0</lineSpacing>
      <selectedIndex>-1</selectedIndex>
      <radius>4</radius>
    </control>
    <control controlID="83E248E8-3EA9-4516-ABF2-232968E03CDE" controlTypeID="Button" x="557" y="552" w="182" h="28" zOrder="7">
      <font family="%E5%BE%AE%E8%BD%AF%E9%9B%85%E9%BB%91" displayName="%E5%BE%AE%E8%BD%AF%E9%9B%85%E9%BB%91" postScript="" weightStyle="Regular" weight="400" isBold="False" isItalic="False"/>
      <text>%E5%95%86%E5%AE%B6%E5%85%A5%E9%A9%BB</text>
      <lineSpacing>0</lineSpacing>
      <selectedIndex>-1</selectedIndex>
      <radius>4</radius>
    </control>
  </controls>
  <param>
    <backgroundColor>4294967295</backgroundColor>
    <fontSize>0</fontSize>
    <fontFamily/>
    <guideLines/>
  </param>
</mockup>